topsis_akash_102218072/__init__.py
topsis_akash_102218072/topsis.py
topsis_akash_102218072-0.2.dist-info/LICENSE
topsis_akash_102218072-0.2.dist-info/METADATA
topsis_akash_102218072-0.2.dist-info/WHEEL
topsis_akash_102218072-0.2.dist-info/entry_points.txt
topsis_akash_102218072-0.2.dist-info/top_level.txt
topsis_akash_102218072-0.2.dist-info/RECORD
