Metadata-Version: 2.1
Name: topsis-akash-102218072
Version: 0.2
Summary: A Python package for TOPSIS method
Author: Akash Khatri
Author-email: akashkhatri2403@gmail.com
Classifier: Programming Language :: Python :: 3
Classifier: License :: OSI Approved :: MIT License
Classifier: Operating System :: OS Independent
Requires-Python: >=3.6
License-File: LICENSE
Requires-Dist: numpy
Requires-Dist: pandas
